pygismo.cpython-312-aarch64-linux-gnu.so
pygismo-25.7.0.dist-info/METADATA
pygismo-25.7.0.dist-info/RECORD
pygismo-25.7.0.dist-info/top_level.txt
pygismo-25.7.0.dist-info/WHEEL
pygismo-25.7.0.dist-info/licenses/LICENSE.txt
